outlier_remover/__init__.py
outlier_remover/outlier_remover.py
outlier_remover_101703283-0.0.0.dist-info/LICENSE.txt
outlier_remover_101703283-0.0.0.dist-info/METADATA
outlier_remover_101703283-0.0.0.dist-info/WHEEL
outlier_remover_101703283-0.0.0.dist-info/entry_points.txt
outlier_remover_101703283-0.0.0.dist-info/top_level.txt
outlier_remover_101703283-0.0.0.dist-info/RECORD
