Metadata-Version: 2.1
Name: outlier-remover-101703283
Version: 0.0.0
Summary: python package for removing outliers from multi-variate data
Home-page: https://pypi.python.org/pypi/outlier_remover_101703283
Author: Katinder Kaur
Author-email: katinder08@gmail.com
License: UNKNOWN
Platform: UNKNOWN
Classifier: Programming Language :: Python :: 3
Classifier: Programming Language :: Python :: 3.6
Classifier: Programming Language :: Python :: 3.7
Classifier: License :: OSI Approved :: MIT License
Classifier: Operating System :: OS Independent
Requires-Python: >=3.6
Requires-Dist: numpy
Requires-Dist: pandas
Requires-Dist: argparse
